LICENSE
README.md
setup.py
web3s/__init__.py
web3s/admin.py
web3s/contract.py
web3s/datastructures.py
web3s/eth.py
web3s/exceptions.py
web3s/iban.py
web3s/main.py
web3s/manager.py
web3s/miner.py
web3s/module.py
web3s/net.py
web3s/parity.py
web3s/personal.py
web3s/pm.py
web3s/shh.py
web3s/testing.py
web3s/txpool.py
web3s/version.py
web3s.egg-info/PKG-INFO
web3s.egg-info/SOURCES.txt
web3s.egg-info/dependency_links.txt
web3s.egg-info/requires.txt
web3s.egg-info/top_level.txt
web3s/gas_strategies/__init__.py
web3s/gas_strategies/rpc.py
web3s/gas_strategies/time_based.py
web3s/middleware/__init__.py
web3s/middleware/abi.py
web3s/middleware/attrdict.py
web3s/middleware/cache.py
web3s/middleware/exception_handling.py
web3s/middleware/exception_retry_request.py
web3s/middleware/fixture.py
web3s/middleware/formatting.py
web3s/middleware/gas_price_strategy.py
web3s/middleware/geth_poa.py
web3s/middleware/names.py
web3s/middleware/normalize_errors.py
web3s/middleware/normalize_request_parameters.py
web3s/middleware/pythonic.py
web3s/middleware/signing.py
web3s/middleware/simulate_unmined_transaction.py
web3s/middleware/stalecheck.py
web3s/middleware/validation.py
web3s/providers/__init__.py
web3s/providers/base.py
web3s/providers/rpc.py
web3s/providers/tester.py
web3s/providers/eth_tester/__init__.py
web3s/providers/eth_tester/defaults.py
web3s/providers/eth_tester/main.py
web3s/providers/eth_tester/middleware.py
web3s/utils/__init__.py
web3s/utils/abi.py
web3s/utils/blocks.py
web3s/utils/caching.py
web3s/utils/contracts.py
web3s/utils/datatypes.py
web3s/utils/decorators.py
web3s/utils/empty.py
web3s/utils/encoding.py
web3s/utils/events.py
web3s/utils/filters.py
web3s/utils/formatters.py
web3s/utils/function_identifiers.py
web3s/utils/http.py
web3s/utils/hypothesis.py
web3s/utils/math.py
web3s/utils/normalizers.py
web3s/utils/request.py
web3s/utils/rpc_abi.py
web3s/utils/threads.py
web3s/utils/transactions.py
web3s/utils/validation.py
web3s/utils/windows.py
web3s/utils/six/__init__.py
web3s/utils/six/six.py
web3s/utils/toolz/__init__.py
web3s/utils/toolz/curried.py